batanalysis/__init__.py
batanalysis/_version.py
batanalysis/attitude.py
batanalysis/bat_dph.py
batanalysis/bat_dpi.py
batanalysis/bat_drm.py
batanalysis/bat_skyimage.py
batanalysis/bat_skyview.py
batanalysis/bat_survey.py
batanalysis/bat_tte.py
batanalysis/batlib.py
batanalysis/batobservation.py
batanalysis/batproducts.py
batanalysis/detectorplanehist.py
batanalysis/mosaic.py
batanalysis/parallel.py
batanalysis/plotting.py
batanalysis/tte_data.py
batanalysis/data/batanalysis_logo.jpg
batanalysis/data/batanalysis_logo.key
batanalysis/data/batanalysis_logo.pdf
batanalysis/data/offaxiscorr_8bin_20061221.img
batanalysis/data/survey6b_2.cat
batanalysis/data/survey6b_2.txt
batanalysis/data/swiftbat_survey_full_157m.rsp
batanalysis/data/batanalysis_logo/batanalysis_logo.001.jpeg
BatAnalysis-2.1.0.dist-info/LICENSE
BatAnalysis-2.1.0.dist-info/METADATA
BatAnalysis-2.1.0.dist-info/WHEEL
BatAnalysis-2.1.0.dist-info/top_level.txt
BatAnalysis-2.1.0.dist-info/RECORD
