Metadata-Version: 2.1
Name: BatAnalysis
Version: 2.1.0
Summary: Routines for analyzing data from BAT on the Neil Gehrels Swift Observatory
Home-page: https://github.com/parsotat/BatAnalysis
Author: Tyler Parsotan and Sibasish Laha
Author-email: tyler.parsotan@nasa.gov
License: BSD-3-Clause
Classifier: Development Status :: 3 - Alpha
Classifier: Intended Audience :: Science/Research
Classifier: Programming Language :: Python
Classifier: Programming Language :: Python :: 3
Classifier: Topic :: Scientific/Engineering :: Astronomy
Requires-Python: >=3.9
License-File: LICENSE
Requires-Dist: setuptools>=58.0.4
Requires-Dist: numpy>=1.24.4
Requires-Dist: matplotlib>=3.4.2
Requires-Dist: astropy>=4.3.1
Requires-Dist: astroquery>=0.4.10
Requires-Dist: swiftbat>=0.1.5
Requires-Dist: swifttools>=3.0.21
Requires-Dist: scipy>=1.7.2
Requires-Dist: requests>=2.20
Requires-Dist: joblib>=1.1.0
Requires-Dist: dpath>=2.1.4
Requires-Dist: histpy>=2.0.2
Requires-Dist: reproject>=0.13.1
Requires-Dist: healpy>=1.16.6
Requires-Dist: mhealpy>=0.3.5
Requires-Dist: astro-gdt-swift>=1.0.1
Requires-Dist: ligo.skymap>=2.1.2
